{
  "User": [
    {
      "id": 1,
      "username": "waldrom68",
      "password": "tomate",
      "admin": false
    },
    {
      "id": 3,
      "username": "Waldomar",
      "password": "tomawdewqte",
      "admin": false
    },
    {
      "id": 4,
      "username": "Eustauio",
      "password": "unaclavedificil",
      "admin": false
    },
    {
      "id": 5,
      "username": "giliperto",
      "password": "tiramelagoma",
      "admin": false
    },
    {
      "id": 6,
      "username": "eltontin",
      "password": "con-la-clave-cortita",
      "admin": true
    },
    {
      "id": 7,
      "username": "layegua",
      "password": "sin-codigo-moral",
      "admin": false
    },
    {
      "id": 8,
      "username": "elputo intento BIS",
      "password": "por enesima vez",
      "admin": false
    }
  ],
  "Studies": [
    {
      "id": 4,
      "start_date": "2022",
      "end_date": "..",
      "institution": "Min. de Desarrollo Productivo y CESSI",
      "degree": "Programador Web full stack JS",
      "level": "Especialización",
      "userId": 1
    },
    {
      "id": 3,
      "start_date": "2021",
      "end_date": "2022",
      "institution": "EDUCACION IT",
      "degree": "Python Web Developer",
      "level": "Especialización",
      "userId": 1
    },
    {
      "id": 2,
      "start_date": "2007",
      "end_date": "2012",
      "institution": "UP",
      "degree": "Maestría en Dirección de Empresas",
      "level": "Posgrado",
      "userId": 1
    },
    {
      "id": 1,
      "start_date": "2000",
      "end_date": "1996",
      "institution": "UCALP",
      "degree": "Analista Universitario de Sistemas",
      "level": "Grado",
      "userId": 1
    }
  ],
  "LaboralCareer": [
    {
      "id": 1,
      "start_date": "09-1993",
      "end_date": "02-2018",
      "organization": "ITBA",
      "position": "Director",
      "userId": 1
    },
    {
      "id": 2,
      "start_date": "09-1990",
      "end_date": "12-1993",
      "organization": "freelance",
      "position": "Programador",
      "userId": 1
    }
  ],
  "PortfolioInit": {
    "id": 1,
    "theme": "Dark",
    "status": true,
    "userId": 1
  },
  "Cards": [
    {
      "id": 1,
      "name": "Perfil",
      "status": false,
      "group": 1,
      "data": "",
      "resume": "",
      "modelTemplate": "lista",
      "userId": 1
    },
    {
      "id": 2,
      "name": "Objetivo",
      "status": false,
      "group": 1,
      "data": "",
      "resume": "",
      "modelTemplate": "lista",
      "userId": 1
    },
    {
      "id": 3,
      "name": "Trayectoria",
      "status": false,
      "group": 1,
      "data": [],
      "modelTemplate": "objeto",
      "userId": 1
    },
    {
      "id": 4,
      "name": "Formación",
      "status": false,
      "group": 1,
      "data": [],
      "resume": "Analista de Sistemas, MBA, Full-Stack",
      "modelTemplate": "lista",
      "userId": 1
    },
    {
      "id": 5,
      "name": "Habilidades tecnicas",
      "status": false,
      "group": 2,
      "data": [],
      "resume": "Python, Django, JS, Java, Angular, SQL, CSS3, HTML",
      "modelTemplate": "lista",
      "userId": 1
    },
    {
      "id": 6,
      "name": "Habilidades personales",
      "status": false,
      "group": 2,
      "data": [],
      "resume": "Persona integra",
      "modelTemplate": "lista",
      "userId": 1
    },
    {
      "id": 7,
      "name": "Proyectos",
      "status": false,
      "group": 2,
      "data": [],
      "resume": "",
      "modelTemplate": "lista",
      "userId": 1
    },
    {
      "id": 8,
      "name": "Intereses",
      "status": false,
      "group": 2,
      "data": [],
      "resume": "",
      "modelTemplate": "lista",
      "userId": 1
    }
  ],
  "DisplayPersonalData": {
    "id": 1,
    "name": true,
    "lastName": false,
    "foto": true,
    "location": true,
    "profession": true,
    "since": true,
    "userId": 1
  },
  "DCO-FRONT-BACK": {
    "DESDE-AQUI-MISMO-FORMATO-A-API-REST": true
  },
  "Person": [
    {
      "id": 4,
      "name": "Eustaquio",
      "lastName": "Baranda",
      "pathFoto": "",
      "location": "Argentina, Bs.As.",
      "profession": "Programador Senior\nCOBOL",
      "profile": "",
      "objetive": "",
      "since": "2005",
      "email": "eustaquib@gmail.com",
      "username": "sadsadad",
      "password": "olvidaclave",
      "displaydata": {
        "id": 4,
        "name": true,
        "lastName": true,
        "photo": true,
        "location": true,
        "profession": true,
        "since": true,
        "theme": "Dark"
      }
    },
    {
      "id": 3,
      "name": "Persona",
      "lastName": "De Prueba",
      "pathFoto": "",
      "location": "Argentina, Bs.As.",
      "profession": "Programador Senior\nCOBOL",
      "profile": "Impresione con el perfil... POR FAVOR",
      "objetive": "Ser claro con el objetivo. PUEDE SER CLAVE",
      "since": "1948",
      "email": "de-prueba@gmail.com",
      "username": "persona",
      "password": "olvidaclave",
      "displaydata": {
        "id": 3,
        "name": true,
        "lastName": true,
        "photo": true,
        "location": true,
        "profession": true,
        "since": true,
        "theme": "Dark"
      }
    },
    {
      "id": 1,
      "name": "Walter",
      "lastName": "Romario",
      "pathFoto": "../assets/images/ico.svg",
      "location": "Argentina, Bs.As.",
      "profession": "Full Stack Developer\nPYTHON - JAVA",
      "profile": "Ocupé cargos de RRHH y disfruté mejorar procesos, generar tableros de control para la toma de decisiones, y hacer de \"una especie de analista funcional\" para servir de enlace entre áreas de negocio y de tecnología. Ciertamente era un Analista Universitario de Sistemas en un área de recursos humanos.\n\nLuego de 24 años trabajando en la universidad, ahora he vuelto a mi esencia: \"creatividad, innovación, sistemas y tecnología\".\n\nEn resumen, además de contar con criterio empresarial tengo conocimientos y experiencia para sumar valor a cualquier proyecto, y quienes me conocen destacarán mi compromiso para alcanzar objetivos, mi lealtad, integridad y disciplina.",
      "objetive": "Me atraen los desafíos y aventuras en donde pueda seguir ayudando, creando, innovando, mejorando ...\nPodés contactarme si tenés alguna idea o propuesta y será un plus si es divertida.",
      "since": "1968",
      "email": "waldrom68@gmail.com",
      "username": "waldrom",
      "password": "sinclave",
      "displaydata": {
        "id": 1,
        "name": false,
        "lastName": true,
        "photo": true,
        "location": true,
        "profession": true,
        "since": true,
        "theme": "Dark"
      }
    }
  ],
  "Interest": [
    {
      "id": 1,
      "name": "Adaptabilidad al clima jeje",
      "orderdeploy": 1,
      "userId": 1
    },
    {
      "id": 2,
      "name": "Viajar",
      "orderdeploy": 1,
      "userId": 1
    },
    {
      "id": 3,
      "name": "culear",
      "orderdeploy": 1,
      "userId": 1
    },
    {
      "id": 4,
      "name": "Colaborar y asistir",
      "orderdeploy": 1,
      "userId": 1
    },
    {
      "id": 6,
      "name": "hacer milanesas a la NAPOLITANA",
      "orderdeploy": 1,
      "userId": 1
    },
    {
      "id": 8,
      "name": "Realizar compras",
      "orderdeploy": 0,
      "userId": 3
    }
  ],
  "SoftSkill": [
    {
      "id": 1,
      "name": "CSS3",
      "assessment": 70,
      "orderdeploy": 0,
      "userId": 1
    },
    {
      "id": 2,
      "name": "Capacidad analítica",
      "assessment": 4,
      "orderdeploy": 0,
      "userId": 1
    },
    {
      "id": 3,
      "name": "Gestión del tiempo",
      "assessment": 4,
      "orderdeploy": 0,
      "userId": 1
    },
    {
      "id": 4,
      "name": "Inteligencia emocional y social",
      "assessment": 4,
      "orderdeploy": 0,
      "userId": 1
    },
    {
      "id": 5,
      "name": "Seguridad personal",
      "assessment": 3,
      "orderdeploy": 0,
      "userId": 1
    },
    {
      "id": 6,
      "name": "Trabajo en equipo",
      "assessment": 3,
      "orderdeploy": 0,
      "userId": 1
    },
    {
      "id": 7,
      "name": "Dibujar hipotenusas en el aire",
      "assessment": 0,
      "orderdeploy": 0,
      "userId": 4
    },
    {
      "id": 8,
      "name": "Escucha activa",
      "assessment": 0,
      "orderdeploy": 0,
      "userId": 4
    },
    {
      "id": 9,
      "name": "Ser o no Ser",
      "assessment": 0,
      "orderdeploy": 0,
      "userId": 4
    },
    {
      "id": 11,
      "name": "Escucha activa",
      "assessment": 3,
      "orderdeploy": 0,
      "userId": 3
    }
  ],
  "HardSkill": [
    {
      "id": 1,
      "name": "CSS 3",
      "assessment": 35,
      "orderdeploy": 0,
      "userId": 1
    },
    {
      "id": 2,
      "name": "Django Framework",
      "assessment": 35,
      "orderdeploy": 0,
      "userId": 1
    },
    {
      "id": 3,
      "name": "HTML",
      "assessment": 70,
      "orderdeploy": 0,
      "userId": 1
    },
    {
      "id": 4,
      "name": "Javascript",
      "assessment": 60,
      "orderdeploy": 0,
      "userId": 1
    },
    {
      "id": 5,
      "name": "Python",
      "assessment": 80,
      "orderdeploy": 0,
      "userId": 1
    },
    {
      "id": 5,
      "name": "Python",
      "assessment": 80,
      "orderdeploy": 0,
      "userId": 1
    },
    {
      "id": 6,
      "name": "Classic Visual Basic",
      "assessment": 25,
      "orderdeploy": 0,
      "userId": 1
    },
    {
      "id": 7,
      "name": "Delphi/Object Pascal",
      "assessment": 100,
      "orderdeploy": 0,
      "userId": 4
    }
  ],
  "Project": [
    {
      "id": 1,
      "name": "Curriculum Vitae. -Static Web Page-",
      "resume": "Elaborado con JS, HTML y CSS",
      "since": "2022",
      "url": "https://waldrom68.github.io/",
      "orderdeploy": 0,
      "userId": 1
    },
    {
      "id": 2,
      "name": "Guia audica para eventos",
      "resume": "Elaborado con el Framework Django, Python, JS, HTML y CSS3",
      "since": "2022",
      "url": "https://waldrom68.pythonanywhere.com/",
      "orderdeploy": 0,
      "userId": 1
    },
    {
      "id": 3,
      "name": "Calculator pro 2000x",
      "resume": "",
      "orderdeploy": 0,
      "since": "2022-12-27T15:50:31.700Z",
      "url": "",
      "userId": 4
    }
  ]
}